[  {    "type": "get",    "url": "/account",    "title": "Get current Account",    "name": "GetCurrentAccount",    "group": "Account",    "version": "1.0.0",    "permission": [      {        "name": "user",        "title": "An account is required.",        "description": ""      }    ],    "success": {      "fields": {        "Success 200": [          {            "group": "Success 200",            "type": "String",            "optional": false,            "field": "username",            "description": ""          },          {            "group": "Success 200",            "type": "String",            "optional": false,            "field": "email",            "description": ""          },          {            "group": "Success 200",            "type": "String",            "optional": false,            "field": "timezone",            "description": ""          },          {            "group": "Success 200",            "type": "Date",            "optional": false,            "field": "register_time",            "description": ""          },          {            "group": "Success 200",            "type": "Date",            "optional": false,            "field": "pro_expires_time",            "description": ""          }        ]      },      "examples": [        {          "title": "Success",          "content": "HTTP/1.1 200 OK\n{\n  \"username\": \"example\",\n  \"email\": \"example@example.com\",\n  \"timezone\": \"Asia/Shanghai\",\n  \"pro_expires_time\": \"2017-01-01T00:00:00.000Z\",\n  \"register_time\": \"2015-06-21T19:38:06.960Z\"\n}",          "type": "json"        }      ]    },    "filename": "src/Account.coffee",    "groupTitle": "Account",    "error": {      "fields": {        "Error 4xx": [          {            "group": "Error 4xx",            "optional": false,            "field": "NotAuthorized",            "description": ""          },          {            "group": "Error 4xx",            "optional": false,            "field": "InvalidCredentials",            "description": ""          }        ]      },      "examples": [        {          "title": "NotAuthorized",          "content": "HTTP/1.1 401 Unauthorized\n\n{\n  \"code\": \"NotAuthorized\",\n  \"message\": \"Unauthorized\",\n  \"description\": \"Unauthorized\",\n  \"errors\": [],\n  \"documentation_url\": \"https://pomotodo.com/developer\"\n}",          "type": "json"        },        {          "title": "InvalidCredentials",          "content": "HTTP/1.1 401 Unauthorized\n\n{\n  \"code\": \"InvalidCredentials\",\n  \"message\": \"Invalid credential\",\n  \"description\": \"Invalid credential\",\n  \"errors\": [],\n  \"documentation_url\": \"https://pomotodo.com/developer\"\n}",          "type": "json"        }      ]    }  },  {    "type": "post",    "url": "/pomos",    "title": "Create a pomo",    "name": "CreatePomo",    "group": "Pomo",    "version": "1.0.0",    "permission": [      {        "name": "pro",        "title": "An account is required with a valid Pro subscription.",        "description": ""      }    ],    "parameter": {      "fields": {        "Parameter": [          {            "group": "Parameter",            "type": "String",            "optional": true,            "field": "timezone",            "description": "<p>The timezone name of the pomo, used for generating local times (<code>local_started_at</code>, <code>local_ended_at</code>) from normal times (<code>started_at</code>, <code>ended_at</code>) if the local times are not provided.</p>"          },          {            "group": "Parameter",            "type": "String",            "optional": true,            "field": "description",            "description": "<p>only required for a normal pomo (<code>abandoned == false</code>)</p>"          }        ]      }    },    "filename": "src/Pomo.coffee",    "groupTitle": "Pomo",    "error": {      "fields": {        "Error 4xx": [          {            "group": "Error 4xx",            "optional": false,            "field": "NotAuthorized",            "description": ""          },          {            "group": "Error 4xx",            "optional": false,            "field": "InvalidCredentials",            "description": ""          },          {            "group": "Error 4xx",            "optional": false,            "field": "ResourceForbidden",            "description": ""          }        ]      },      "examples": [        {          "title": "NotAuthorized",          "content": "HTTP/1.1 401 Unauthorized\n\n{\n  \"code\": \"NotAuthorized\",\n  \"message\": \"Unauthorized\",\n  \"description\": \"Unauthorized\",\n  \"errors\": [],\n  \"documentation_url\": \"https://pomotodo.com/developer\"\n}",          "type": "json"        },        {          "title": "InvalidCredentials",          "content": "HTTP/1.1 401 Unauthorized\n\n{\n  \"code\": \"InvalidCredentials\",\n  \"message\": \"Invalid credential\",\n  \"description\": \"Invalid credential\",\n  \"errors\": [],\n  \"documentation_url\": \"https://pomotodo.com/developer\"\n}",          "type": "json"        },        {          "title": "ResourceForbidden",          "content": "HTTP/1.1 403 Forbidden\n\n{\n  \"code\": \"ResourceForbidden\",\n  \"message\": \"A valid Pro subscription is required\",\n  \"description\": \"A valid Pro subscription is required\",\n  \"errors\": [],\n  \"documentation_url\": \"https://pomotodo.com/developer\"\n}",          "type": "json"        }      ]    },    "success": {      "fields": {        "Success 200": [          {            "group": "Success 200",            "type": "UUID",            "optional": false,            "field": "uuid",            "description": ""          },          {            "group": "Success 200",            "type": "Date",            "optional": false,            "field": "created_at",            "description": ""          },          {            "group": "Success 200",            "type": "Date",            "optional": false,            "field": "updated_at",            "description": ""          },          {            "group": "Success 200",            "type": "String",            "optional": true,            "field": "description",            "description": "<p>only required for a normal pomo (<code>abandoned == false</code>)</p>"          },          {            "group": "Success 200",            "type": "Date",            "optional": false,            "field": "started_at",            "description": ""          },          {            "group": "Success 200",            "type": "Date",            "optional": false,            "field": "ended_at",            "description": ""          },          {            "group": "Success 200",            "type": "Date",            "optional": false,            "field": "local_started_at",            "description": "<p>local time stored in the UTC</p>"          },          {            "group": "Success 200",            "type": "Date",            "optional": false,            "field": "local_ended_at",            "description": "<p>local time stored in the UTC</p>"          },          {            "group": "Success 200",            "type": "Number",            "optional": false,            "field": "length",            "description": "<p>length in seconds</p>"          },          {            "group": "Success 200",            "type": "Boolean",            "optional": true,            "field": "abandoned",            "defaultValue": "false",            "description": "<p>is abandoned?</p>"          },          {            "group": "Success 200",            "type": "Boolean",            "optional": true,            "field": "manual",            "defaultValue": "true",            "description": "<p>is manually added?</p>"          }        ]      },      "examples": [        {          "title": "Success",          "content": "HTTP/1.1 201 OK\nLocation: /1/pomos/deadcafe-dead-cafe-dead-cafedeadcafe\n\n{\n  \"uuid\": \"deadcafe-dead-cafe-dead-cafedeadcafe\",\n  \"created_at\": \"2016-08-06T10:00:00.000Z\"\n  \"updated_at\": \"2016-08-06T10:00:00.000Z\"\n  \"description\": \"Hello Pomotodo!\",\n  \"started_at\": \"2016-08-06T10:00:00.000Z\",\n  \"ended_at\": \"2016-08-06T10:00:00.000Z\",\n  \"local_started_at\": \"2016-08-06T18:00:00.000Z\",\n  \"local_ended_at\": \"2016-08-06T18:00:00.000Z\",\n  \"length\": 1500,\n  \"abandoned\": false,\n  \"manual\": false\n}",          "type": "json"        }      ]    }  },  {    "type": "delete",    "url": "/pomos/:uuid",    "title": "Delete a pomo",    "name": "DeletePomo",    "group": "Pomo",    "version": "1.0.0",    "permission": [      {        "name": "pro",        "title": "An account is required with a valid Pro subscription.",        "description": ""      }    ],    "success": {      "examples": [        {          "title": "Success",          "content": "HTTP/1.1 204 No Content",          "type": "json"        }      ]    },    "filename": "src/Pomo.coffee",    "groupTitle": "Pomo",    "error": {      "fields": {        "Error 4xx": [          {            "group": "Error 4xx",            "optional": false,            "field": "NotAuthorized",            "description": ""          },          {            "group": "Error 4xx",            "optional": false,            "field": "InvalidCredentials",            "description": ""          },          {            "group": "Error 4xx",            "optional": false,            "field": "ResourceForbidden",            "description": ""          },          {            "group": "Error 4xx",            "optional": false,            "field": "ResourceNotFound",            "description": ""          }        ]      },      "examples": [        {          "title": "NotAuthorized",          "content": "HTTP/1.1 401 Unauthorized\n\n{\n  \"code\": \"NotAuthorized\",\n  \"message\": \"Unauthorized\",\n  \"description\": \"Unauthorized\",\n  \"errors\": [],\n  \"documentation_url\": \"https://pomotodo.com/developer\"\n}",          "type": "json"        },        {          "title": "InvalidCredentials",          "content": "HTTP/1.1 401 Unauthorized\n\n{\n  \"code\": \"InvalidCredentials\",\n  \"message\": \"Invalid credential\",\n  \"description\": \"Invalid credential\",\n  \"errors\": [],\n  \"documentation_url\": \"https://pomotodo.com/developer\"\n}",          "type": "json"        },        {          "title": "ResourceForbidden",          "content": "HTTP/1.1 403 Forbidden\n\n{\n  \"code\": \"ResourceForbidden\",\n  \"message\": \"A valid Pro subscription is required\",\n  \"description\": \"A valid Pro subscription is required\",\n  \"errors\": [],\n  \"documentation_url\": \"https://pomotodo.com/developer\"\n}",          "type": "json"        },        {          "title": "ResourceNotFound",          "content": "HTTP/1.1 404 Not Found\n\n{\n  \"code\": \"ResourceNotFound\",\n  \"message\": \"Requested resource cannot be found\",\n  \"description\": \"Requested resource cannot be found\",\n  \"errors\": [],\n  \"documentation_url\": \"https://pomotodo.com/developer\"\n}",          "type": "json"        }      ]    },    "parameter": {      "fields": {        "Parameter": [          {            "group": "Parameter",            "type": "UUID",            "optional": false,            "field": "uuid",            "description": ""          }        ]      }    }  },  {    "type": "get",    "url": "/pomos/:uuid",    "title": "Get a pomo",    "name": "GetPomo",    "group": "Pomo",    "version": "1.0.0",    "permission": [      {        "name": "pro",        "title": "An account is required with a valid Pro subscription.",        "description": ""      }    ],    "description": "<p>Get a pomo by its UUID.</p>",    "filename": "src/Pomo.coffee",    "groupTitle": "Pomo",    "error": {      "fields": {        "Error 4xx": [          {            "group": "Error 4xx",            "optional": false,            "field": "NotAuthorized",            "description": ""          },          {            "group": "Error 4xx",            "optional": false,            "field": "InvalidCredentials",            "description": ""          },          {            "group": "Error 4xx",            "optional": false,            "field": "ResourceForbidden",            "description": ""          },          {            "group": "Error 4xx",            "optional": false,            "field": "ResourceNotFound",            "description": ""          }        ]      },      "examples": [        {          "title": "NotAuthorized",          "content": "HTTP/1.1 401 Unauthorized\n\n{\n  \"code\": \"NotAuthorized\",\n  \"message\": \"Unauthorized\",\n  \"description\": \"Unauthorized\",\n  \"errors\": [],\n  \"documentation_url\": \"https://pomotodo.com/developer\"\n}",          "type": "json"        },        {          "title": "InvalidCredentials",          "content": "HTTP/1.1 401 Unauthorized\n\n{\n  \"code\": \"InvalidCredentials\",\n  \"message\": \"Invalid credential\",\n  \"description\": \"Invalid credential\",\n  \"errors\": [],\n  \"documentation_url\": \"https://pomotodo.com/developer\"\n}",          "type": "json"        },        {          "title": "ResourceForbidden",          "content": "HTTP/1.1 403 Forbidden\n\n{\n  \"code\": \"ResourceForbidden\",\n  \"message\": \"A valid Pro subscription is required\",\n  \"description\": \"A valid Pro subscription is required\",\n  \"errors\": [],\n  \"documentation_url\": \"https://pomotodo.com/developer\"\n}",          "type": "json"        },        {          "title": "ResourceNotFound",          "content": "HTTP/1.1 404 Not Found\n\n{\n  \"code\": \"ResourceNotFound\",\n  \"message\": \"Requested resource cannot be found\",\n  \"description\": \"Requested resource cannot be found\",\n  \"errors\": [],\n  \"documentation_url\": \"https://pomotodo.com/developer\"\n}",          "type": "json"        }      ]    },    "parameter": {      "fields": {        "Parameter": [          {            "group": "Parameter",            "type": "UUID",            "optional": false,            "field": "uuid",            "description": ""          }        ]      }    },    "success": {      "fields": {        "Success 200": [          {            "group": "Success 200",            "type": "UUID",            "optional": false,            "field": "uuid",            "description": ""          },          {            "group": "Success 200",            "type": "Date",            "optional": false,            "field": "created_at",            "description": ""          },          {            "group": "Success 200",            "type": "Date",            "optional": false,            "field": "updated_at",            "description": ""          },          {            "group": "Success 200",            "type": "String",            "optional": true,            "field": "description",            "description": "<p>only required for a normal pomo (<code>abandoned == false</code>)</p>"          },          {            "group": "Success 200",            "type": "Date",            "optional": false,            "field": "started_at",            "description": ""          },          {            "group": "Success 200",            "type": "Date",            "optional": false,            "field": "ended_at",            "description": ""          },          {            "group": "Success 200",            "type": "Date",            "optional": false,            "field": "local_started_at",            "description": "<p>local time stored in the UTC</p>"          },          {            "group": "Success 200",            "type": "Date",            "optional": false,            "field": "local_ended_at",            "description": "<p>local time stored in the UTC</p>"          },          {            "group": "Success 200",            "type": "Number",            "optional": false,            "field": "length",            "description": "<p>length in seconds</p>"          },          {            "group": "Success 200",            "type": "Boolean",            "optional": true,            "field": "abandoned",            "defaultValue": "false",            "description": "<p>is abandoned?</p>"          },          {            "group": "Success 200",            "type": "Boolean",            "optional": true,            "field": "manual",            "defaultValue": "true",            "description": "<p>is manually added?</p>"          }        ]      },      "examples": [        {          "title": "Success",          "content": "HTTP/1.1 200 OK\n\n{\n  \"uuid\": \"deadcafe-dead-cafe-dead-cafedeadcafe\",\n  \"created_at\": \"2016-08-06T10:00:00.000Z\"\n  \"updated_at\": \"2016-08-06T10:00:00.000Z\"\n  \"description\": \"Hello Pomotodo!\",\n  \"started_at\": \"2016-08-06T10:00:00.000Z\",\n  \"ended_at\": \"2016-08-06T10:00:00.000Z\",\n  \"local_started_at\": \"2016-08-06T18:00:00.000Z\",\n  \"local_ended_at\": \"2016-08-06T18:00:00.000Z\",\n  \"length\": 1500,\n  \"abandoned\": false,\n  \"manual\": false\n}",          "type": "json"        }      ]    }  },  {    "type": "get",    "url": "/pomos",    "title": "List all pomos",    "name": "ListPomos",    "group": "Pomo",    "version": "1.0.0",    "permission": [      {        "name": "pro",        "title": "An account is required with a valid Pro subscription.",        "description": ""      }    ],    "parameter": {      "fields": {        "Parameter": [          {            "group": "Parameter",            "type": "Boolean",            "optional": true,            "field": "abandoned",            "defaultValue": "false",            "description": ""          },          {            "group": "Parameter",            "type": "Boolean",            "optional": true,            "field": "manual",            "defaultValue": "false",            "description": ""          },          {            "group": "Parameter",            "type": "Date",            "optional": true,            "field": "started_later_than",            "description": "<p>If there's no time filtering options are specified at all, <code>started_later_than</code> would be the local start time of the current month of the user.</p>"          },          {            "group": "Parameter",            "type": "Date",            "optional": true,            "field": "started_earlier_than",            "description": ""          },          {            "group": "Parameter",            "type": "Date",            "optional": true,            "field": "ended_later_than",            "description": ""          },          {            "group": "Parameter",            "type": "Date",            "optional": true,            "field": "ended_earlier_than",            "description": ""          }        ]      }    },    "description": "<p>List all pomos, in the order that they started counting.</p>",    "filename": "src/Pomo.coffee",    "groupTitle": "Pomo",    "error": {      "fields": {        "Error 4xx": [          {            "group": "Error 4xx",            "optional": false,            "field": "NotAuthorized",            "description": ""          },          {            "group": "Error 4xx",            "optional": false,            "field": "InvalidCredentials",            "description": ""          },          {            "group": "Error 4xx",            "optional": false,            "field": "ResourceForbidden",            "description": ""          }        ]      },      "examples": [        {          "title": "NotAuthorized",          "content": "HTTP/1.1 401 Unauthorized\n\n{\n  \"code\": \"NotAuthorized\",\n  \"message\": \"Unauthorized\",\n  \"description\": \"Unauthorized\",\n  \"errors\": [],\n  \"documentation_url\": \"https://pomotodo.com/developer\"\n}",          "type": "json"        },        {          "title": "InvalidCredentials",          "content": "HTTP/1.1 401 Unauthorized\n\n{\n  \"code\": \"InvalidCredentials\",\n  \"message\": \"Invalid credential\",\n  \"description\": \"Invalid credential\",\n  \"errors\": [],\n  \"documentation_url\": \"https://pomotodo.com/developer\"\n}",          "type": "json"        },        {          "title": "ResourceForbidden",          "content": "HTTP/1.1 403 Forbidden\n\n{\n  \"code\": \"ResourceForbidden\",\n  \"message\": \"A valid Pro subscription is required\",\n  \"description\": \"A valid Pro subscription is required\",\n  \"errors\": [],\n  \"documentation_url\": \"https://pomotodo.com/developer\"\n}",          "type": "json"        }      ]    },    "success": {      "fields": {        "Success 200": [          {            "group": "Success 200",            "type": "UUID",            "optional": false,            "field": "uuid",            "description": ""          },          {            "group": "Success 200",            "type": "Date",            "optional": false,            "field": "created_at",            "description": ""          },          {            "group": "Success 200",            "type": "Date",            "optional": false,            "field": "updated_at",            "description": ""          },          {            "group": "Success 200",            "type": "String",            "optional": true,            "field": "description",            "description": "<p>only required for a normal pomo (<code>abandoned == false</code>)</p>"          },          {            "group": "Success 200",            "type": "Date",            "optional": false,            "field": "started_at",            "description": ""          },          {            "group": "Success 200",            "type": "Date",            "optional": false,            "field": "ended_at",            "description": ""          },          {            "group": "Success 200",            "type": "Date",            "optional": false,            "field": "local_started_at",            "description": "<p>local time stored in the UTC</p>"          },          {            "group": "Success 200",            "type": "Date",            "optional": false,            "field": "local_ended_at",            "description": "<p>local time stored in the UTC</p>"          },          {            "group": "Success 200",            "type": "Number",            "optional": false,            "field": "length",            "description": "<p>length in seconds</p>"          },          {            "group": "Success 200",            "type": "Boolean",            "optional": true,            "field": "abandoned",            "defaultValue": "false",            "description": "<p>is abandoned?</p>"          },          {            "group": "Success 200",            "type": "Boolean",            "optional": true,            "field": "manual",            "defaultValue": "true",            "description": "<p>is manually added?</p>"          }        ]      },      "examples": [        {          "title": "Success",          "content": "HTTP/1.1 200 OK\nX-Resource-Count: 5\nLink: </1/pomos?offset=0&limit=20&abandoned=false&manual=false>; rel=\"first\", \n      </1/pomos?offset=0&limit=20&abandoned=false&manual=false>; rel=\"last\"\n\n[\n  {\n    \"uuid\": \"deadcafe-dead-cafe-dead-cafedeadcafe\",\n    \"created_at\": \"2016-08-06T10:00:00.000Z\"\n    \"updated_at\": \"2016-08-06T10:00:00.000Z\"\n    \"description\": \"Hello Pomotodo!\",\n    \"started_at\": \"2016-08-06T10:00:00.000Z\",\n    \"ended_at\": \"2016-08-06T10:00:00.000Z\",\n    \"local_started_at\": \"2016-08-06T18:00:00.000Z\",\n    \"local_ended_at\": \"2016-08-06T18:00:00.000Z\",\n    \"length\": 1500,\n    \"abandoned\": false,\n    \"manual\": false\n  }\n]",          "type": "json"        }      ]    }  },  {    "type": "patch",    "url": "/pomos/:uuid",    "title": "Edit a pomo",    "name": "UpdatePomo",    "group": "Pomo",    "version": "1.0.0",    "permission": [      {        "name": "pro",        "title": "An account is required with a valid Pro subscription.",        "description": ""      }    ],    "filename": "src/Pomo.coffee",    "groupTitle": "Pomo",    "error": {      "fields": {        "Error 4xx": [          {            "group": "Error 4xx",            "optional": false,            "field": "NotAuthorized",            "description": ""          },          {            "group": "Error 4xx",            "optional": false,            "field": "InvalidCredentials",            "description": ""          },          {            "group": "Error 4xx",            "optional": false,            "field": "ResourceForbidden",            "description": ""          },          {            "group": "Error 4xx",            "optional": false,            "field": "ResourceNotFound",            "description": ""          },          {            "group": "Error 4xx",            "optional": false,            "field": "InvalidContent",            "description": ""          }        ]      },      "examples": [        {          "title": "NotAuthorized",          "content": "HTTP/1.1 401 Unauthorized\n\n{\n  \"code\": \"NotAuthorized\",\n  \"message\": \"Unauthorized\",\n  \"description\": \"Unauthorized\",\n  \"errors\": [],\n  \"documentation_url\": \"https://pomotodo.com/developer\"\n}",          "type": "json"        },        {          "title": "InvalidCredentials",          "content": "HTTP/1.1 401 Unauthorized\n\n{\n  \"code\": \"InvalidCredentials\",\n  \"message\": \"Invalid credential\",\n  \"description\": \"Invalid credential\",\n  \"errors\": [],\n  \"documentation_url\": \"https://pomotodo.com/developer\"\n}",          "type": "json"        },        {          "title": "ResourceForbidden",          "content": "HTTP/1.1 403 Forbidden\n\n{\n  \"code\": \"ResourceForbidden\",\n  \"message\": \"A valid Pro subscription is required\",\n  \"description\": \"A valid Pro subscription is required\",\n  \"errors\": [],\n  \"documentation_url\": \"https://pomotodo.com/developer\"\n}",          "type": "json"        },        {          "title": "ResourceNotFound",          "content": "HTTP/1.1 404 Not Found\n\n{\n  \"code\": \"ResourceNotFound\",\n  \"message\": \"Requested resource cannot be found\",\n  \"description\": \"Requested resource cannot be found\",\n  \"errors\": [],\n  \"documentation_url\": \"https://pomotodo.com/developer\"\n}",          "type": "json"        },        {          "title": "InvalidContent",          "content": "HTTP/1.1 422 Unprocessable Entity\n\n{\n  \"code\": \"InvalidContent\",\n  \"message\": \"Validation failed\",\n  \"description\": \"Validation failed\",\n  \"errors\": [\n    {\n      \"path\": \"uuid\",\n      \"type\": \"invalid\",\n      \"message\": \"\\\"uuid\\\" with value \\\"xxxxxxxx-xxxx-xxxx-xxxx-xxxxxxxxxxxx\\\" fails to match the required pattern: ...\"\n    }\n  ],\n  \"documentation_url\": \"https://pomotodo.com/developer\"\n}",          "type": "json"        }      ]    },    "parameter": {      "fields": {        "Parameter": [          {            "group": "Parameter",            "type": "UUID",            "optional": false,            "field": "uuid",            "description": ""          },          {            "group": "Parameter",            "type": "String",            "optional": true,            "field": "description",            "description": "<p>only required for a normal pomo (<code>abandoned == false</code>)</p>"          }        ]      }    },    "success": {      "fields": {        "Success 200": [          {            "group": "Success 200",            "type": "UUID",            "optional": false,            "field": "uuid",            "description": ""          },          {            "group": "Success 200",            "type": "Date",            "optional": false,            "field": "created_at",            "description": ""          },          {            "group": "Success 200",            "type": "Date",            "optional": false,            "field": "updated_at",            "description": ""          },          {            "group": "Success 200",            "type": "String",            "optional": true,            "field": "description",            "description": "<p>only required for a normal pomo (<code>abandoned == false</code>)</p>"          },          {            "group": "Success 200",            "type": "Date",            "optional": false,            "field": "started_at",            "description": ""          },          {            "group": "Success 200",            "type": "Date",            "optional": false,            "field": "ended_at",            "description": ""          },          {            "group": "Success 200",            "type": "Date",            "optional": false,            "field": "local_started_at",            "description": "<p>local time stored in the UTC</p>"          },          {            "group": "Success 200",            "type": "Date",            "optional": false,            "field": "local_ended_at",            "description": "<p>local time stored in the UTC</p>"          },          {            "group": "Success 200",            "type": "Number",            "optional": false,            "field": "length",            "description": "<p>length in seconds</p>"          },          {            "group": "Success 200",            "type": "Boolean",            "optional": true,            "field": "abandoned",            "defaultValue": "false",            "description": "<p>is abandoned?</p>"          },          {            "group": "Success 200",            "type": "Boolean",            "optional": true,            "field": "manual",            "defaultValue": "true",            "description": "<p>is manually added?</p>"          }        ]      },      "examples": [        {          "title": "Success",          "content": "HTTP/1.1 200 OK\n\n{\n  \"uuid\": \"deadcafe-dead-cafe-dead-cafedeadcafe\",\n  \"created_at\": \"2016-08-06T10:00:00.000Z\"\n  \"updated_at\": \"2016-08-06T10:00:00.000Z\"\n  \"description\": \"Hello Pomotodo!\",\n  \"started_at\": \"2016-08-06T10:00:00.000Z\",\n  \"ended_at\": \"2016-08-06T10:00:00.000Z\",\n  \"local_started_at\": \"2016-08-06T18:00:00.000Z\",\n  \"local_ended_at\": \"2016-08-06T18:00:00.000Z\",\n  \"length\": 1500,\n  \"abandoned\": false,\n  \"manual\": false\n}",          "type": "json"        }      ]    }  },  {    "type": "post",    "url": "/todos/:parent_uuid/sub_todos",    "title": "Create a sub-todo in the todo",    "name": "CreateSubTodo",    "group": "SubTodo",    "version": "1.0.0",    "permission": [      {        "name": "pro",        "title": "An account is required with a valid Pro subscription.",        "description": ""      }    ],    "filename": "src/SubTodo.coffee",    "groupTitle": "SubTodo",    "error": {      "fields": {        "Error 4xx": [          {            "group": "Error 4xx",            "optional": false,            "field": "NotAuthorized",            "description": ""          },          {            "group": "Error 4xx",            "optional": false,            "field": "InvalidCredentials",            "description": ""          },          {            "group": "Error 4xx",            "optional": false,            "field": "ResourceForbidden",            "description": ""          },          {            "group": "Error 4xx",            "optional": false,            "field": "InvalidContent",            "description": ""          }        ]      },      "examples": [        {          "title": "NotAuthorized",          "content": "HTTP/1.1 401 Unauthorized\n\n{\n  \"code\": \"NotAuthorized\",\n  \"message\": \"Unauthorized\",\n  \"description\": \"Unauthorized\",\n  \"errors\": [],\n  \"documentation_url\": \"https://pomotodo.com/developer\"\n}",          "type": "json"        },        {          "title": "InvalidCredentials",          "content": "HTTP/1.1 401 Unauthorized\n\n{\n  \"code\": \"InvalidCredentials\",\n  \"message\": \"Invalid credential\",\n  \"description\": \"Invalid credential\",\n  \"errors\": [],\n  \"documentation_url\": \"https://pomotodo.com/developer\"\n}",          "type": "json"        },        {          "title": "ResourceForbidden",          "content": "HTTP/1.1 403 Forbidden\n\n{\n  \"code\": \"ResourceForbidden\",\n  \"message\": \"A valid Pro subscription is required\",\n  \"description\": \"A valid Pro subscription is required\",\n  \"errors\": [],\n  \"documentation_url\": \"https://pomotodo.com/developer\"\n}",          "type": "json"        },        {          "title": "InvalidContent",          "content": "HTTP/1.1 422 Unprocessable Entity\n\n{\n  \"code\": \"InvalidContent\",\n  \"message\": \"Validation failed\",\n  \"description\": \"Validation failed\",\n  \"errors\": [\n    {\n      \"path\": \"uuid\",\n      \"type\": \"invalid\",\n      \"message\": \"\\\"uuid\\\" with value \\\"xxxxxxxx-xxxx-xxxx-xxxx-xxxxxxxxxxxx\\\" fails to match the required pattern: ...\"\n    }\n  ],\n  \"documentation_url\": \"https://pomotodo.com/developer\"\n}",          "type": "json"        }      ]    },    "parameter": {      "fields": {        "Parameter": [          {            "group": "Parameter",            "type": "String",            "optional": false,            "field": "description",            "description": ""          },          {            "group": "Parameter",            "type": "Boolean",            "optional": true,            "field": "completed",            "defaultValue": "false",            "description": ""          },          {            "group": "Parameter",            "type": "Date",            "optional": true,            "field": "completed_at",            "description": ""          }        ]      }    },    "success": {      "fields": {        "Success 200": [          {            "group": "Success 200",            "type": "UUID",            "optional": false,            "field": "uuid",            "description": ""          },          {            "group": "Success 200",            "type": "UUID",            "optional": false,            "field": "parent_uuid",            "description": ""          },          {            "group": "Success 200",            "type": "Date",            "optional": false,            "field": "created_at",            "description": ""          },          {            "group": "Success 200",            "type": "Date",            "optional": false,            "field": "updated_at",            "description": ""          },          {            "group": "Success 200",            "type": "String",            "optional": false,            "field": "description",            "description": ""          },          {            "group": "Success 200",            "type": "Boolean",            "optional": true,            "field": "completed",            "defaultValue": "false",            "description": ""          },          {            "group": "Success 200",            "type": "Date",            "optional": true,            "field": "completed_at",            "description": ""          }        ]      },      "examples": [        {          "title": "Success",          "content": "HTTP/1.1 201 OK\nLocation: /todos/ac753187-2f22-4b5c-b716-f1fcecfb4410/sub_todos/81921b2e-8b54-46cf-bb47-0d3c3c7e8302\n\n{\n  \"uuid\": \"ff59811e-4c53-404f-a842-9590b632616f\",\n  \"parent_uuid\": \"ac753187-2f22-4b5c-b716-f1fcecfb4410\",\n  \"created_at\": \"2016-08-06T06:51:12.000Z\",\n  \"updated_at\": \"2016-08-06T06:51:12.000Z\",\n  \"description\": \"Catch an orzFly\",\n  \"completed\": false,\n  \"completed_at\": null\n}",          "type": "json"        }      ]    }  },  {    "type": "delete",    "url": "/todos/:parent_uuid/sub_todos/:uuid",    "title": "Delete a sub-todo in the todo",    "name": "DeleteSubTodo",    "group": "SubTodo",    "version": "1.0.0",    "permission": [      {        "name": "pro",        "title": "An account is required with a valid Pro subscription.",        "description": ""      }    ],    "success": {      "examples": [        {          "title": "Success",          "content": "HTTP/1.1 204 No Content",          "type": "json"        }      ]    },    "filename": "src/SubTodo.coffee",    "groupTitle": "SubTodo",    "error": {      "fields": {        "Error 4xx": [          {            "group": "Error 4xx",            "optional": false,            "field": "NotAuthorized",            "description": ""          },          {            "group": "Error 4xx",            "optional": false,            "field": "InvalidCredentials",            "description": ""          },          {            "group": "Error 4xx",            "optional": false,            "field": "ResourceForbidden",            "description": ""          }        ]      },      "examples": [        {          "title": "NotAuthorized",          "content": "HTTP/1.1 401 Unauthorized\n\n{\n  \"code\": \"NotAuthorized\",\n  \"message\": \"Unauthorized\",\n  \"description\": \"Unauthorized\",\n  \"errors\": [],\n  \"documentation_url\": \"https://pomotodo.com/developer\"\n}",          "type": "json"        },        {          "title": "InvalidCredentials",          "content": "HTTP/1.1 401 Unauthorized\n\n{\n  \"code\": \"InvalidCredentials\",\n  \"message\": \"Invalid credential\",\n  \"description\": \"Invalid credential\",\n  \"errors\": [],\n  \"documentation_url\": \"https://pomotodo.com/developer\"\n}",          "type": "json"        },        {          "title": "ResourceForbidden",          "content": "HTTP/1.1 403 Forbidden\n\n{\n  \"code\": \"ResourceForbidden\",\n  \"message\": \"A valid Pro subscription is required\",\n  \"description\": \"A valid Pro subscription is required\",\n  \"errors\": [],\n  \"documentation_url\": \"https://pomotodo.com/developer\"\n}",          "type": "json"        }      ]    },    "parameter": {      "fields": {        "Parameter": [          {            "group": "Parameter",            "type": "UUID",            "optional": false,            "field": "uuid",            "description": ""          },          {            "group": "Parameter",            "type": "UUID",            "optional": false,            "field": "parent_uuid",            "description": ""          }        ]      }    }  },  {    "type": "get",    "url": "/todos/:parent_uuid/sub_todos/:uuid",    "title": "Get a sub-todo in the todo",    "name": "GetSubTodo",    "group": "SubTodo",    "version": "1.0.0",    "permission": [      {        "name": "pro",        "title": "An account is required with a valid Pro subscription.",        "description": ""      }    ],    "parameter": {      "fields": {        "Parameter": [          {            "group": "Parameter",            "type": "UUID",            "optional": false,            "field": "parent_uuid",            "description": ""          },          {            "group": "Parameter",            "type": "UUID",            "optional": false,            "field": "uuid",            "description": ""          }        ]      }    },    "filename": "src/SubTodo.coffee",    "groupTitle": "SubTodo",    "error": {      "fields": {        "Error 4xx": [          {            "group": "Error 4xx",            "optional": false,            "field": "NotAuthorized",            "description": ""          },          {            "group": "Error 4xx",            "optional": false,            "field": "InvalidCredentials",            "description": ""          },          {            "group": "Error 4xx",            "optional": false,            "field": "ResourceForbidden",            "description": ""          }        ]      },      "examples": [        {          "title": "NotAuthorized",          "content": "HTTP/1.1 401 Unauthorized\n\n{\n  \"code\": \"NotAuthorized\",\n  \"message\": \"Unauthorized\",\n  \"description\": \"Unauthorized\",\n  \"errors\": [],\n  \"documentation_url\": \"https://pomotodo.com/developer\"\n}",          "type": "json"        },        {          "title": "InvalidCredentials",          "content": "HTTP/1.1 401 Unauthorized\n\n{\n  \"code\": \"InvalidCredentials\",\n  \"message\": \"Invalid credential\",\n  \"description\": \"Invalid credential\",\n  \"errors\": [],\n  \"documentation_url\": \"https://pomotodo.com/developer\"\n}",          "type": "json"        },        {          "title": "ResourceForbidden",          "content": "HTTP/1.1 403 Forbidden\n\n{\n  \"code\": \"ResourceForbidden\",\n  \"message\": \"A valid Pro subscription is required\",\n  \"description\": \"A valid Pro subscription is required\",\n  \"errors\": [],\n  \"documentation_url\": \"https://pomotodo.com/developer\"\n}",          "type": "json"        }      ]    },    "success": {      "fields": {        "Success 200": [          {            "group": "Success 200",            "type": "UUID",            "optional": false,            "field": "uuid",            "description": ""          },          {            "group": "Success 200",            "type": "UUID",            "optional": false,            "field": "parent_uuid",            "description": ""          },          {            "group": "Success 200",            "type": "Date",            "optional": false,            "field": "created_at",            "description": ""          },          {            "group": "Success 200",            "type": "Date",            "optional": false,            "field": "updated_at",            "description": ""          },          {            "group": "Success 200",            "type": "String",            "optional": false,            "field": "description",            "description": ""          },          {            "group": "Success 200",            "type": "Boolean",            "optional": true,            "field": "completed",            "defaultValue": "false",            "description": ""          },          {            "group": "Success 200",            "type": "Date",            "optional": true,            "field": "completed_at",            "description": ""          }        ]      },      "examples": [        {          "title": "Success",          "content": "HTTP/1.1 200 OK\n\n{\n  \"uuid\": \"ff59811e-4c53-404f-a842-9590b632616f\",\n  \"parent_uuid\": \"ac753187-2f22-4b5c-b716-f1fcecfb4410\",\n  \"created_at\": \"2016-08-06T06:51:12.000Z\",\n  \"updated_at\": \"2016-08-06T06:51:12.000Z\",\n  \"description\": \"Catch an orzFly\",\n  \"completed\": false,\n  \"completed_at\": null\n}",          "type": "json"        }      ]    }  },  {    "type": "get",    "url": "/todos/:parent_uuid/sub_todos",    "title": "List all sub-todos in the todo",    "name": "ListSubTodos",    "group": "SubTodo",    "version": "1.0.0",    "permission": [      {        "name": "pro",        "title": "An account is required with a valid Pro subscription.",        "description": ""      }    ],    "parameter": {      "fields": {        "Parameter": [          {            "group": "Parameter",            "type": "UUID",            "optional": false,            "field": "parent_uuid",            "description": ""          }        ]      }    },    "filename": "src/SubTodo.coffee",    "groupTitle": "SubTodo",    "error": {      "fields": {        "Error 4xx": [          {            "group": "Error 4xx",            "optional": false,            "field": "NotAuthorized",            "description": ""          },          {            "group": "Error 4xx",            "optional": false,            "field": "InvalidCredentials",            "description": ""          },          {            "group": "Error 4xx",            "optional": false,            "field": "ResourceForbidden",            "description": ""          }        ]      },      "examples": [        {          "title": "NotAuthorized",          "content": "HTTP/1.1 401 Unauthorized\n\n{\n  \"code\": \"NotAuthorized\",\n  \"message\": \"Unauthorized\",\n  \"description\": \"Unauthorized\",\n  \"errors\": [],\n  \"documentation_url\": \"https://pomotodo.com/developer\"\n}",          "type": "json"        },        {          "title": "InvalidCredentials",          "content": "HTTP/1.1 401 Unauthorized\n\n{\n  \"code\": \"InvalidCredentials\",\n  \"message\": \"Invalid credential\",\n  \"description\": \"Invalid credential\",\n  \"errors\": [],\n  \"documentation_url\": \"https://pomotodo.com/developer\"\n}",          "type": "json"        },        {          "title": "ResourceForbidden",          "content": "HTTP/1.1 403 Forbidden\n\n{\n  \"code\": \"ResourceForbidden\",\n  \"message\": \"A valid Pro subscription is required\",\n  \"description\": \"A valid Pro subscription is required\",\n  \"errors\": [],\n  \"documentation_url\": \"https://pomotodo.com/developer\"\n}",          "type": "json"        }      ]    },    "success": {      "fields": {        "Success 200": [          {            "group": "Success 200",            "type": "UUID",            "optional": false,            "field": "uuid",            "description": ""          },          {            "group": "Success 200",            "type": "UUID",            "optional": false,            "field": "parent_uuid",            "description": ""          },          {            "group": "Success 200",            "type": "Date",            "optional": false,            "field": "created_at",            "description": ""          },          {            "group": "Success 200",            "type": "Date",            "optional": false,            "field": "updated_at",            "description": ""          },          {            "group": "Success 200",            "type": "String",            "optional": false,            "field": "description",            "description": ""          },          {            "group": "Success 200",            "type": "Boolean",            "optional": true,            "field": "completed",            "defaultValue": "false",            "description": ""          },          {            "group": "Success 200",            "type": "Date",            "optional": true,            "field": "completed_at",            "description": ""          }        ]      },      "examples": [        {          "title": "Success",          "content": "HTTP/1.1 200 OK\n\n[\n  {\n    \"uuid\": \"ff59811e-4c53-404f-a842-9590b632616f\",\n    \"parent_uuid\": \"ac753187-2f22-4b5c-b716-f1fcecfb4410\",\n    \"created_at\": \"2016-08-06T06:51:12.000Z\",\n    \"updated_at\": \"2016-08-06T06:51:12.000Z\",\n    \"description\": \"Catch an orzFly\",\n    \"completed\": false,\n    \"completed_at\": null\n  }\n]",          "type": "json"        }      ]    }  },  {    "type": "patch",    "url": "/todos/:parent_uuid/sub_todos/:uuid",    "title": "Edit a sub-todo in the todo",    "name": "UpdateSubTodo",    "group": "SubTodo",    "version": "1.0.0",    "permission": [      {        "name": "pro",        "title": "An account is required with a valid Pro subscription.",        "description": ""      }    ],    "filename": "src/SubTodo.coffee",    "groupTitle": "SubTodo",    "error": {      "fields": {        "Error 4xx": [          {            "group": "Error 4xx",            "optional": false,            "field": "NotAuthorized",            "description": ""          },          {            "group": "Error 4xx",            "optional": false,            "field": "InvalidCredentials",            "description": ""          },          {            "group": "Error 4xx",            "optional": false,            "field": "ResourceForbidden",            "description": ""          }        ]      },      "examples": [        {          "title": "NotAuthorized",          "content": "HTTP/1.1 401 Unauthorized\n\n{\n  \"code\": \"NotAuthorized\",\n  \"message\": \"Unauthorized\",\n  \"description\": \"Unauthorized\",\n  \"errors\": [],\n  \"documentation_url\": \"https://pomotodo.com/developer\"\n}",          "type": "json"        },        {          "title": "InvalidCredentials",          "content": "HTTP/1.1 401 Unauthorized\n\n{\n  \"code\": \"InvalidCredentials\",\n  \"message\": \"Invalid credential\",\n  \"description\": \"Invalid credential\",\n  \"errors\": [],\n  \"documentation_url\": \"https://pomotodo.com/developer\"\n}",          "type": "json"        },        {          "title": "ResourceForbidden",          "content": "HTTP/1.1 403 Forbidden\n\n{\n  \"code\": \"ResourceForbidden\",\n  \"message\": \"A valid Pro subscription is required\",\n  \"description\": \"A valid Pro subscription is required\",\n  \"errors\": [],\n  \"documentation_url\": \"https://pomotodo.com/developer\"\n}",          "type": "json"        }      ]    },    "parameter": {      "fields": {        "Parameter": [          {            "group": "Parameter",            "type": "UUID",            "optional": false,            "field": "uuid",            "description": ""          },          {            "group": "Parameter",            "type": "UUID",            "optional": false,            "field": "parent_uuid",            "description": ""          },          {            "group": "Parameter",            "type": "String",            "optional": true,            "field": "description",            "description": ""          },          {            "group": "Parameter",            "type": "Boolean",            "optional": true,            "field": "completed",            "defaultValue": "false",            "description": ""          },          {            "group": "Parameter",            "type": "Date",            "optional": true,            "field": "completed_at",            "description": ""          }        ]      }    },    "success": {      "fields": {        "Success 200": [          {            "group": "Success 200",            "type": "UUID",            "optional": false,            "field": "uuid",            "description": ""          },          {            "group": "Success 200",            "type": "UUID",            "optional": false,            "field": "parent_uuid",            "description": ""          },          {            "group": "Success 200",            "type": "Date",            "optional": false,            "field": "created_at",            "description": ""          },          {            "group": "Success 200",            "type": "Date",            "optional": false,            "field": "updated_at",            "description": ""          },          {            "group": "Success 200",            "type": "String",            "optional": false,            "field": "description",            "description": ""          },          {            "group": "Success 200",            "type": "Boolean",            "optional": true,            "field": "completed",            "defaultValue": "false",            "description": ""          },          {            "group": "Success 200",            "type": "Date",            "optional": true,            "field": "completed_at",            "description": ""          }        ]      },      "examples": [        {          "title": "Success",          "content": "HTTP/1.1 200 OK\n\n{\n  \"uuid\": \"ff59811e-4c53-404f-a842-9590b632616f\",\n  \"parent_uuid\": \"ac753187-2f22-4b5c-b716-f1fcecfb4410\",\n  \"created_at\": \"2016-08-06T06:51:12.000Z\",\n  \"updated_at\": \"2016-08-06T06:51:12.000Z\",\n  \"description\": \"Catch an orzFly\",\n  \"completed\": false,\n  \"completed_at\": null\n}",          "type": "json"        }      ]    }  },  {    "type": "post",    "url": "/todos",    "title": "Create a todo",    "name": "CreateTodos",    "group": "Todo",    "version": "1.0.0",    "permission": [      {        "name": "pro",        "title": "An account is required with a valid Pro subscription.",        "description": ""      }    ],    "filename": "src/Todo.coffee",    "groupTitle": "Todo",    "error": {      "fields": {        "Error 4xx": [          {            "group": "Error 4xx",            "optional": false,            "field": "NotAuthorized",            "description": ""          },          {            "group": "Error 4xx",            "optional": false,            "field": "InvalidCredentials",            "description": ""          },          {            "group": "Error 4xx",            "optional": false,            "field": "ResourceForbidden",            "description": ""          },          {            "group": "Error 4xx",            "optional": false,            "field": "InvalidContent",            "description": ""          }        ]      },      "examples": [        {          "title": "NotAuthorized",          "content": "HTTP/1.1 401 Unauthorized\n\n{\n  \"code\": \"NotAuthorized\",\n  \"message\": \"Unauthorized\",\n  \"description\": \"Unauthorized\",\n  \"errors\": [],\n  \"documentation_url\": \"https://pomotodo.com/developer\"\n}",          "type": "json"        },        {          "title": "InvalidCredentials",          "content": "HTTP/1.1 401 Unauthorized\n\n{\n  \"code\": \"InvalidCredentials\",\n  \"message\": \"Invalid credential\",\n  \"description\": \"Invalid credential\",\n  \"errors\": [],\n  \"documentation_url\": \"https://pomotodo.com/developer\"\n}",          "type": "json"        },        {          "title": "ResourceForbidden",          "content": "HTTP/1.1 403 Forbidden\n\n{\n  \"code\": \"ResourceForbidden\",\n  \"message\": \"A valid Pro subscription is required\",\n  \"description\": \"A valid Pro subscription is required\",\n  \"errors\": [],\n  \"documentation_url\": \"https://pomotodo.com/developer\"\n}",          "type": "json"        },        {          "title": "InvalidContent",          "content": "HTTP/1.1 422 Unprocessable Entity\n\n{\n  \"code\": \"InvalidContent\",\n  \"message\": \"Validation failed\",\n  \"description\": \"Validation failed\",\n  \"errors\": [\n    {\n      \"path\": \"uuid\",\n      \"type\": \"invalid\",\n      \"message\": \"\\\"uuid\\\" with value \\\"xxxxxxxx-xxxx-xxxx-xxxx-xxxxxxxxxxxx\\\" fails to match the required pattern: ...\"\n    }\n  ],\n  \"documentation_url\": \"https://pomotodo.com/developer\"\n}",          "type": "json"        }      ]    },    "parameter": {      "fields": {        "Parameter": [          {            "group": "Parameter",            "type": "String",            "optional": false,            "field": "description",            "description": ""          },          {            "group": "Parameter",            "type": "String",            "optional": true,            "field": "notice",            "defaultValue": "null",            "description": ""          },          {            "group": "Parameter",            "type": "Boolean",            "optional": true,            "field": "pin",            "defaultValue": "false",            "description": ""          },          {            "group": "Parameter",            "type": "Boolean",            "optional": true,            "field": "completed",            "defaultValue": "false",            "description": ""          },          {            "group": "Parameter",            "type": "Date",            "optional": true,            "field": "completed_at",            "description": ""          },          {            "group": "Parameter",            "type": "String",            "allowedValues": [              "\"none\"",              "\"each_day\"",              "\"each_week\"",              "\"each_two_week\"",              "\"each_month\"",              "\"each_year\""            ],            "optional": true,            "field": "repeat_type",            "defaultValue": "none",            "description": ""          },          {            "group": "Parameter",            "type": "Date",            "optional": true,            "field": "remind_time",            "defaultValue": "null",            "description": ""          },          {            "group": "Parameter",            "type": "Number",            "optional": true,            "field": "estimated_pomo_count",            "defaultValue": "null",            "description": ""          },          {            "group": "Parameter",            "type": "Number",            "optional": true,            "field": "costed_pomo_count",            "defaultValue": "null",            "description": ""          }        ]      }    },    "success": {      "fields": {        "Success 200": [          {            "group": "Success 200",            "type": "UUID",            "optional": false,            "field": "uuid",            "description": ""          },          {            "group": "Success 200",            "type": "Date",            "optional": false,            "field": "created_at",            "description": ""          },          {            "group": "Success 200",            "type": "Date",            "optional": false,            "field": "updated_at",            "description": ""          },          {            "group": "Success 200",            "type": "String",            "optional": false,            "field": "description",            "description": ""          },          {            "group": "Success 200",            "type": "String",            "optional": true,            "field": "notice",            "defaultValue": "null",            "description": ""          },          {            "group": "Success 200",            "type": "Boolean",            "optional": true,            "field": "pin",            "defaultValue": "false",            "description": ""          },          {            "group": "Success 200",            "type": "Boolean",            "optional": true,            "field": "completed",            "defaultValue": "false",            "description": ""          },          {            "group": "Success 200",            "type": "Date",            "optional": true,            "field": "completed_at",            "description": ""          },          {            "group": "Success 200",            "type": "String",            "allowedValues": [              "\"none\"",              "\"each_day\"",              "\"each_week\"",              "\"each_two_week\"",              "\"each_month\"",              "\"each_year\""            ],            "optional": true,            "field": "repeat_type",            "defaultValue": "none",            "description": ""          },          {            "group": "Success 200",            "type": "Date",            "optional": true,            "field": "remind_time",            "defaultValue": "null",            "description": ""          },          {            "group": "Success 200",            "type": "Number",            "optional": true,            "field": "estimated_pomo_count",            "defaultValue": "null",            "description": ""          },          {            "group": "Success 200",            "type": "Number",            "optional": true,            "field": "costed_pomo_count",            "defaultValue": "null",            "description": ""          }        ]      },      "examples": [        {          "title": "Success",          "content": "HTTP/1.1 201 OK\nLocation: /todos/ac753187-2f22-4b5c-b716-f1fcecfb4410\n\n{\n  \"uuid\": \"ac753187-2f22-4b5c-b716-f1fcecfb4410\",\n  \"created_at\": \"2016-08-06T06:48:52.000Z\",\n  \"updated_at\": \"2016-08-06T06:51:12.000Z\",\n  \"description\": \"Catch some little Monsters\",\n  \"notice\": null,\n  \"pin\": false,\n  \"completed\": false,\n  \"completed_at\": null,\n  \"repeat_type\": \"none\",\n  \"remind_time\": null,\n  \"estimated_pomo_count\": null,\n  \"costed_pomo_count\": 0,\n  \"sub_todos\": [\n    \"81921b2e-8b54-46cf-bb47-0d3c3c7e8302\",\n    \"ff59811e-4c53-404f-a842-9590b632616f\"\n  ]\n}",          "type": "json"        }      ]    }  },  {    "type": "delete",    "url": "/todos/:uuid",    "title": "Delete a todo",    "name": "DeleteTodo",    "group": "Todo",    "version": "1.0.0",    "permission": [      {        "name": "pro",        "title": "An account is required with a valid Pro subscription.",        "description": ""      }    ],    "success": {      "examples": [        {          "title": "Success",          "content": "HTTP/1.1 204 No Content",          "type": "json"        }      ]    },    "filename": "src/Todo.coffee",    "groupTitle": "Todo",    "error": {      "fields": {        "Error 4xx": [          {            "group": "Error 4xx",            "optional": false,            "field": "NotAuthorized",            "description": ""          },          {            "group": "Error 4xx",            "optional": false,            "field": "InvalidCredentials",            "description": ""          },          {            "group": "Error 4xx",            "optional": false,            "field": "ResourceForbidden",            "description": ""          },          {            "group": "Error 4xx",            "optional": false,            "field": "ResourceNotFound",            "description": ""          }        ]      },      "examples": [        {          "title": "NotAuthorized",          "content": "HTTP/1.1 401 Unauthorized\n\n{\n  \"code\": \"NotAuthorized\",\n  \"message\": \"Unauthorized\",\n  \"description\": \"Unauthorized\",\n  \"errors\": [],\n  \"documentation_url\": \"https://pomotodo.com/developer\"\n}",          "type": "json"        },        {          "title": "InvalidCredentials",          "content": "HTTP/1.1 401 Unauthorized\n\n{\n  \"code\": \"InvalidCredentials\",\n  \"message\": \"Invalid credential\",\n  \"description\": \"Invalid credential\",\n  \"errors\": [],\n  \"documentation_url\": \"https://pomotodo.com/developer\"\n}",          "type": "json"        },        {          "title": "ResourceForbidden",          "content": "HTTP/1.1 403 Forbidden\n\n{\n  \"code\": \"ResourceForbidden\",\n  \"message\": \"A valid Pro subscription is required\",\n  \"description\": \"A valid Pro subscription is required\",\n  \"errors\": [],\n  \"documentation_url\": \"https://pomotodo.com/developer\"\n}",          "type": "json"        },        {          "title": "ResourceNotFound",          "content": "HTTP/1.1 404 Not Found\n\n{\n  \"code\": \"ResourceNotFound\",\n  \"message\": \"Requested resource cannot be found\",\n  \"description\": \"Requested resource cannot be found\",\n  \"errors\": [],\n  \"documentation_url\": \"https://pomotodo.com/developer\"\n}",          "type": "json"        }      ]    },    "parameter": {      "fields": {        "Parameter": [          {            "group": "Parameter",            "type": "UUID",            "optional": false,            "field": "uuid",            "description": ""          }        ]      }    }  },  {    "type": "get",    "url": "/todos/:uuid",    "title": "Get a todo",    "name": "GetTodo",    "group": "Todo",    "version": "1.0.0",    "permission": [      {        "name": "pro",        "title": "An account is required with a valid Pro subscription.",        "description": ""      }    ],    "filename": "src/Todo.coffee",    "groupTitle": "Todo",    "error": {      "fields": {        "Error 4xx": [          {            "group": "Error 4xx",            "optional": false,            "field": "NotAuthorized",            "description": ""          },          {            "group": "Error 4xx",            "optional": false,            "field": "InvalidCredentials",            "description": ""          },          {            "group": "Error 4xx",            "optional": false,            "field": "ResourceForbidden",            "description": ""          },          {            "group": "Error 4xx",            "optional": false,            "field": "ResourceNotFound",            "description": ""          }        ]      },      "examples": [        {          "title": "NotAuthorized",          "content": "HTTP/1.1 401 Unauthorized\n\n{\n  \"code\": \"NotAuthorized\",\n  \"message\": \"Unauthorized\",\n  \"description\": \"Unauthorized\",\n  \"errors\": [],\n  \"documentation_url\": \"https://pomotodo.com/developer\"\n}",          "type": "json"        },        {          "title": "InvalidCredentials",          "content": "HTTP/1.1 401 Unauthorized\n\n{\n  \"code\": \"InvalidCredentials\",\n  \"message\": \"Invalid credential\",\n  \"description\": \"Invalid credential\",\n  \"errors\": [],\n  \"documentation_url\": \"https://pomotodo.com/developer\"\n}",          "type": "json"        },        {          "title": "ResourceForbidden",          "content": "HTTP/1.1 403 Forbidden\n\n{\n  \"code\": \"ResourceForbidden\",\n  \"message\": \"A valid Pro subscription is required\",\n  \"description\": \"A valid Pro subscription is required\",\n  \"errors\": [],\n  \"documentation_url\": \"https://pomotodo.com/developer\"\n}",          "type": "json"        },        {          "title": "ResourceNotFound",          "content": "HTTP/1.1 404 Not Found\n\n{\n  \"code\": \"ResourceNotFound\",\n  \"message\": \"Requested resource cannot be found\",\n  \"description\": \"Requested resource cannot be found\",\n  \"errors\": [],\n  \"documentation_url\": \"https://pomotodo.com/developer\"\n}",          "type": "json"        }      ]    },    "parameter": {      "fields": {        "Parameter": [          {            "group": "Parameter",            "type": "UUID",            "optional": false,            "field": "uuid",            "description": ""          }        ]      }    },    "success": {      "fields": {        "Success 200": [          {            "group": "Success 200",            "type": "UUID",            "optional": false,            "field": "uuid",            "description": ""          },          {            "group": "Success 200",            "type": "Date",            "optional": false,            "field": "created_at",            "description": ""          },          {            "group": "Success 200",            "type": "Date",            "optional": false,            "field": "updated_at",            "description": ""          },          {            "group": "Success 200",            "type": "String",            "optional": false,            "field": "description",            "description": ""          },          {            "group": "Success 200",            "type": "String",            "optional": true,            "field": "notice",            "defaultValue": "null",            "description": ""          },          {            "group": "Success 200",            "type": "Boolean",            "optional": true,            "field": "pin",            "defaultValue": "false",            "description": ""          },          {            "group": "Success 200",            "type": "Boolean",            "optional": true,            "field": "completed",            "defaultValue": "false",            "description": ""          },          {            "group": "Success 200",            "type": "Date",            "optional": true,            "field": "completed_at",            "description": ""          },          {            "group": "Success 200",            "type": "String",            "allowedValues": [              "\"none\"",              "\"each_day\"",              "\"each_week\"",              "\"each_two_week\"",              "\"each_month\"",              "\"each_year\""            ],            "optional": true,            "field": "repeat_type",            "defaultValue": "none",            "description": ""          },          {            "group": "Success 200",            "type": "Date",            "optional": true,            "field": "remind_time",            "defaultValue": "null",            "description": ""          },          {            "group": "Success 200",            "type": "Number",            "optional": true,            "field": "estimated_pomo_count",            "defaultValue": "null",            "description": ""          },          {            "group": "Success 200",            "type": "Number",            "optional": true,            "field": "costed_pomo_count",            "defaultValue": "null",            "description": ""          }        ]      },      "examples": [        {          "title": "Success",          "content": "HTTP/1.1 200 OK\n\n{\n  \"uuid\": \"ac753187-2f22-4b5c-b716-f1fcecfb4410\",\n  \"created_at\": \"2016-08-06T06:48:52.000Z\",\n  \"updated_at\": \"2016-08-06T06:51:12.000Z\",\n  \"description\": \"Catch some little Monsters\",\n  \"notice\": null,\n  \"pin\": false,\n  \"completed\": false,\n  \"completed_at\": null,\n  \"repeat_type\": \"none\",\n  \"remind_time\": null,\n  \"estimated_pomo_count\": null,\n  \"costed_pomo_count\": 0,\n  \"sub_todos\": [\n    \"81921b2e-8b54-46cf-bb47-0d3c3c7e8302\",\n    \"ff59811e-4c53-404f-a842-9590b632616f\"\n  ]\n}",          "type": "json"        }      ]    }  },  {    "type": "get",    "url": "/todos",    "title": "List all todos",    "name": "ListTodos",    "group": "Todo",    "version": "1.0.0",    "permission": [      {        "name": "pro",        "title": "An account is required with a valid Pro subscription.",        "description": ""      }    ],    "parameter": {      "fields": {        "Parameter": [          {            "group": "Parameter",            "type": "Boolean",            "optional": true,            "field": "completed",            "defaultValue": "false",            "description": ""          },          {            "group": "Parameter",            "type": "Date",            "optional": true,            "field": "completed_later_than",            "description": "<p>If <code>completed == true</code>, this defaults to be the local start time of the current month of the user.</p>"          },          {            "group": "Parameter",            "type": "Date",            "optional": true,            "field": "completed_earlier_than",            "description": "<p>If <code>completed == true</code>, this defaults to be the local end time of the current month of the user.</p>"          }        ]      }    },    "filename": "src/Todo.coffee",    "groupTitle": "Todo",    "error": {      "fields": {        "Error 4xx": [          {            "group": "Error 4xx",            "optional": false,            "field": "NotAuthorized",            "description": ""          },          {            "group": "Error 4xx",            "optional": false,            "field": "InvalidCredentials",            "description": ""          },          {            "group": "Error 4xx",            "optional": false,            "field": "ResourceForbidden",            "description": ""          }        ]      },      "examples": [        {          "title": "NotAuthorized",          "content": "HTTP/1.1 401 Unauthorized\n\n{\n  \"code\": \"NotAuthorized\",\n  \"message\": \"Unauthorized\",\n  \"description\": \"Unauthorized\",\n  \"errors\": [],\n  \"documentation_url\": \"https://pomotodo.com/developer\"\n}",          "type": "json"        },        {          "title": "InvalidCredentials",          "content": "HTTP/1.1 401 Unauthorized\n\n{\n  \"code\": \"InvalidCredentials\",\n  \"message\": \"Invalid credential\",\n  \"description\": \"Invalid credential\",\n  \"errors\": [],\n  \"documentation_url\": \"https://pomotodo.com/developer\"\n}",          "type": "json"        },        {          "title": "ResourceForbidden",          "content": "HTTP/1.1 403 Forbidden\n\n{\n  \"code\": \"ResourceForbidden\",\n  \"message\": \"A valid Pro subscription is required\",\n  \"description\": \"A valid Pro subscription is required\",\n  \"errors\": [],\n  \"documentation_url\": \"https://pomotodo.com/developer\"\n}",          "type": "json"        }      ]    },    "success": {      "fields": {        "Success 200": [          {            "group": "Success 200",            "type": "UUID",            "optional": false,            "field": "uuid",            "description": ""          },          {            "group": "Success 200",            "type": "Date",            "optional": false,            "field": "created_at",            "description": ""          },          {            "group": "Success 200",            "type": "Date",            "optional": false,            "field": "updated_at",            "description": ""          },          {            "group": "Success 200",            "type": "String",            "optional": false,            "field": "description",            "description": ""          },          {            "group": "Success 200",            "type": "String",            "optional": true,            "field": "notice",            "defaultValue": "null",            "description": ""          },          {            "group": "Success 200",            "type": "Boolean",            "optional": true,            "field": "pin",            "defaultValue": "false",            "description": ""          },          {            "group": "Success 200",            "type": "Boolean",            "optional": true,            "field": "completed",            "defaultValue": "false",            "description": ""          },          {            "group": "Success 200",            "type": "Date",            "optional": true,            "field": "completed_at",            "description": ""          },          {            "group": "Success 200",            "type": "String",            "allowedValues": [              "\"none\"",              "\"each_day\"",              "\"each_week\"",              "\"each_two_week\"",              "\"each_month\"",              "\"each_year\""            ],            "optional": true,            "field": "repeat_type",            "defaultValue": "none",            "description": ""          },          {            "group": "Success 200",            "type": "Date",            "optional": true,            "field": "remind_time",            "defaultValue": "null",            "description": ""          },          {            "group": "Success 200",            "type": "Number",            "optional": true,            "field": "estimated_pomo_count",            "defaultValue": "null",            "description": ""          },          {            "group": "Success 200",            "type": "Number",            "optional": true,            "field": "costed_pomo_count",            "defaultValue": "null",            "description": ""          }        ]      },      "examples": [        {          "title": "Success",          "content": "HTTP/1.1 200 OK\n\n[\n  {\n    \"uuid\": \"ac753187-2f22-4b5c-b716-f1fcecfb4410\",\n    \"created_at\": \"2016-08-06T06:48:52.000Z\",\n    \"updated_at\": \"2016-08-06T06:51:12.000Z\",\n    \"description\": \"Catch some little Monsters\",\n    \"notice\": null,\n    \"pin\": false,\n    \"completed\": false,\n    \"completed_at\": null,\n    \"repeat_type\": \"none\",\n    \"remind_time\": null,\n    \"estimated_pomo_count\": null,\n    \"costed_pomo_count\": 0,\n    \"sub_todos\": [\n      \"81921b2e-8b54-46cf-bb47-0d3c3c7e8302\",\n      \"ff59811e-4c53-404f-a842-9590b632616f\"\n    ]\n  }\n]",          "type": "json"        }      ]    }  },  {    "type": "patch",    "url": "/todos/:uuid",    "title": "Edit a todo",    "name": "UpdateTodo",    "group": "Todo",    "version": "1.0.0",    "permission": [      {        "name": "pro",        "title": "An account is required with a valid Pro subscription.",        "description": ""      }    ],    "filename": "src/Todo.coffee",    "groupTitle": "Todo",    "error": {      "fields": {        "Error 4xx": [          {            "group": "Error 4xx",            "optional": false,            "field": "NotAuthorized",            "description": ""          },          {            "group": "Error 4xx",            "optional": false,            "field": "InvalidCredentials",            "description": ""          },          {            "group": "Error 4xx",            "optional": false,            "field": "ResourceForbidden",            "description": ""          },          {            "group": "Error 4xx",            "optional": false,            "field": "ResourceNotFound",            "description": ""          },          {            "group": "Error 4xx",            "optional": false,            "field": "InvalidContent",            "description": ""          }        ]      },      "examples": [        {          "title": "NotAuthorized",          "content": "HTTP/1.1 401 Unauthorized\n\n{\n  \"code\": \"NotAuthorized\",\n  \"message\": \"Unauthorized\",\n  \"description\": \"Unauthorized\",\n  \"errors\": [],\n  \"documentation_url\": \"https://pomotodo.com/developer\"\n}",          "type": "json"        },        {          "title": "InvalidCredentials",          "content": "HTTP/1.1 401 Unauthorized\n\n{\n  \"code\": \"InvalidCredentials\",\n  \"message\": \"Invalid credential\",\n  \"description\": \"Invalid credential\",\n  \"errors\": [],\n  \"documentation_url\": \"https://pomotodo.com/developer\"\n}",          "type": "json"        },        {          "title": "ResourceForbidden",          "content": "HTTP/1.1 403 Forbidden\n\n{\n  \"code\": \"ResourceForbidden\",\n  \"message\": \"A valid Pro subscription is required\",\n  \"description\": \"A valid Pro subscription is required\",\n  \"errors\": [],\n  \"documentation_url\": \"https://pomotodo.com/developer\"\n}",          "type": "json"        },        {          "title": "ResourceNotFound",          "content": "HTTP/1.1 404 Not Found\n\n{\n  \"code\": \"ResourceNotFound\",\n  \"message\": \"Requested resource cannot be found\",\n  \"description\": \"Requested resource cannot be found\",\n  \"errors\": [],\n  \"documentation_url\": \"https://pomotodo.com/developer\"\n}",          "type": "json"        },        {          "title": "InvalidContent",          "content": "HTTP/1.1 422 Unprocessable Entity\n\n{\n  \"code\": \"InvalidContent\",\n  \"message\": \"Validation failed\",\n  \"description\": \"Validation failed\",\n  \"errors\": [\n    {\n      \"path\": \"uuid\",\n      \"type\": \"invalid\",\n      \"message\": \"\\\"uuid\\\" with value \\\"xxxxxxxx-xxxx-xxxx-xxxx-xxxxxxxxxxxx\\\" fails to match the required pattern: ...\"\n    }\n  ],\n  \"documentation_url\": \"https://pomotodo.com/developer\"\n}",          "type": "json"        }      ]    },    "parameter": {      "fields": {        "Parameter": [          {            "group": "Parameter",            "type": "UUID",            "optional": false,            "field": "uuid",            "description": ""          },          {            "group": "Parameter",            "type": "String",            "optional": true,            "field": "description",            "description": ""          },          {            "group": "Parameter",            "type": "String",            "optional": true,            "field": "notice",            "defaultValue": "null",            "description": ""          },          {            "group": "Parameter",            "type": "Boolean",            "optional": true,            "field": "pin",            "defaultValue": "false",            "description": ""          },          {            "group": "Parameter",            "type": "Boolean",            "optional": true,            "field": "completed",            "defaultValue": "false",            "description": ""          },          {            "group": "Parameter",            "type": "Date",            "optional": true,            "field": "completed_at",            "description": ""          },          {            "group": "Parameter",            "type": "String",            "allowedValues": [              "\"none\"",              "\"each_day\"",              "\"each_week\"",              "\"each_two_week\"",              "\"each_month\"",              "\"each_year\""            ],            "optional": true,            "field": "repeat_type",            "defaultValue": "none",            "description": ""          },          {            "group": "Parameter",            "type": "Date",            "optional": true,            "field": "remind_time",            "defaultValue": "null",            "description": ""          },          {            "group": "Parameter",            "type": "Number",            "optional": true,            "field": "estimated_pomo_count",            "defaultValue": "null",            "description": ""          },          {            "group": "Parameter",            "type": "Number",            "optional": true,            "field": "costed_pomo_count",            "defaultValue": "null",            "description": ""          }        ]      }    },    "success": {      "fields": {        "Success 200": [          {            "group": "Success 200",            "type": "UUID",            "optional": false,            "field": "uuid",            "description": ""          },          {            "group": "Success 200",            "type": "Date",            "optional": false,            "field": "created_at",            "description": ""          },          {            "group": "Success 200",            "type": "Date",            "optional": false,            "field": "updated_at",            "description": ""          },          {            "group": "Success 200",            "type": "String",            "optional": false,            "field": "description",            "description": ""          },          {            "group": "Success 200",            "type": "String",            "optional": true,            "field": "notice",            "defaultValue": "null",            "description": ""          },          {            "group": "Success 200",            "type": "Boolean",            "optional": true,            "field": "pin",            "defaultValue": "false",            "description": ""          },          {            "group": "Success 200",            "type": "Boolean",            "optional": true,            "field": "completed",            "defaultValue": "false",            "description": ""          },          {            "group": "Success 200",            "type": "Date",            "optional": true,            "field": "completed_at",            "description": ""          },          {            "group": "Success 200",            "type": "String",            "allowedValues": [              "\"none\"",              "\"each_day\"",              "\"each_week\"",              "\"each_two_week\"",              "\"each_month\"",              "\"each_year\""            ],            "optional": true,            "field": "repeat_type",            "defaultValue": "none",            "description": ""          },          {            "group": "Success 200",            "type": "Date",            "optional": true,            "field": "remind_time",            "defaultValue": "null",            "description": ""          },          {            "group": "Success 200",            "type": "Number",            "optional": true,            "field": "estimated_pomo_count",            "defaultValue": "null",            "description": ""          },          {            "group": "Success 200",            "type": "Number",            "optional": true,            "field": "costed_pomo_count",            "defaultValue": "null",            "description": ""          }        ]      },      "examples": [        {          "title": "Success",          "content": "HTTP/1.1 200 OK\n\n{\n  \"uuid\": \"ac753187-2f22-4b5c-b716-f1fcecfb4410\",\n  \"created_at\": \"2016-08-06T06:48:52.000Z\",\n  \"updated_at\": \"2016-08-06T06:51:12.000Z\",\n  \"description\": \"Catch some little Monsters\",\n  \"notice\": null,\n  \"pin\": false,\n  \"completed\": false,\n  \"completed_at\": null,\n  \"repeat_type\": \"none\",\n  \"remind_time\": null,\n  \"estimated_pomo_count\": null,\n  \"costed_pomo_count\": 0,\n  \"sub_todos\": [\n    \"81921b2e-8b54-46cf-bb47-0d3c3c7e8302\",\n    \"ff59811e-4c53-404f-a842-9590b632616f\"\n  ]\n}",          "type": "json"        }      ]    }  }]
